aetherling/HaskellEpilogue.py
aetherling/HaskellPrelude.py
aetherling/__init__.py
aetherling-0.0.1.dist-info/LICENSE
aetherling-0.0.1.dist-info/METADATA
aetherling-0.0.1.dist-info/WHEEL
aetherling-0.0.1.dist-info/top_level.txt
aetherling-0.0.1.dist-info/RECORD
