Metadata-Version: 2.1
Name: aetherling
Version: 0.0.1
Summary: Aetherling: a DSL for compiling data-parallel programs to hardware accelerators.
Home-page: https://github.com/David-Durst/aetherling
Author: David Durst
Author-email: davidbdurst@gmail.com
License: BSD License
Platform: UNKNOWN
Requires-Python: >=3.7
Requires-Dist: magma-lang (>=1.0.18)
Requires-Dist: coreir
Requires-Dist: fault
Requires-Dist: mantle
Requires-Dist: numpy
Requires-Dist: Pillow
Requires-Dist: bitarray
Requires-Dist: colorlog
Requires-Dist: pytest
